[{"fnumber": "F20", "jhnumber": "JH417", "museumid": "s0548S2019", "title": "Peasant Burning Weeds", "start": "1883-10-01", "end": "1883-10-30", "display": "October 1883", "location": "http://vangoghmuseum.nl/data/term/2210", "current_owner": "http://vocab.getty.edu/ulan/500275558", "link": "https://vangoghworldwide.org/data/artwork/F20"}, {"fnumber": "F147", "jhnumber": "JH891", "museumid": "s0452S1995", "title": "Woman Lifting Potatoes", "start": "1885-07-21", "end": "1885-08-31", "display": "late July - August 1885", "location": "http://vangoghmuseum.nl/data/term/1", "current_owner": "http://vocab.getty.edu/ulan/500275558", "link": "https://vangoghworldwide.org/data/artwork/F147"}, {"fnumber": "F723", "jhnumber": "JH1722", "museumid": "s0417N1990", "title": "View of the Alpilles", "start": "1890-02-01", "end": "1890-02-28", "display": "February 1890", "location": "http://vangoghmuseum.nl/data/term/2229", "current_owner": "http://vocab.getty.edu/ulan/500275558", "link": "https://vangoghworldwide.org/data/artwork/F723"}, {"fnumber": "F216c", "jhnumber": "JH1082", "museumid": "s0202V1962", "title": "Horse", "start": "1886-06-11", "end": "1886-06-20", "display": "mid June 1886", "location": "http://vangoghmuseum.nl/data/term/2221", "current_owner": "http://vocab.getty.edu/ulan/500275558", "link": "https://vangoghworldwide.org/data/artwork/F216c"}, {"fnumber": "F216j", "jhnumber": "JH1059", "museumid": "s0201V1962", "title": "Torso of Venus", "start": "1886-06-11", "end": "1886-06-20", "display": "mid June 1886", "location": "http://vangoghmuseum.nl/data/term/2221", "current_owner": "http://vocab.getty.edu/ulan/500275558", "link": "https://vangoghworldwide.org/data/artwork/F216j"}, {"fnumber": "F546", "jhnumber": null, "museumid": "s0257V1962", "title": "Portrait of Gauguin", "start": "1888-11-29", "end": "1888-12-03", "display": "circa 1 December 1888", "location": "http://vangoghmuseum.nl/data/term/41", "current_owner": "http://vocab.getty.edu/ulan/500275558", "link": "https://vangoghworldwide.org/data/artwork/F546"}, {"fnumber": "F4", "jhnumber": "JH187", "museumid": "s0416N1990", "title": "View of the Sea at Scheveningen", "start": "1882-08-21", "end": "1882-08-22", "display": "21 August or 22 August 1882", "location": "http://vangoghmuseum.nl/data/term/3554", "current_owner": "http://vocab.getty.edu/ulan/500275558", "link": "https://vangoghworldwide.org/data/artwork/F4"}, {"fnumber": "F159", "jhnumber": null, "museumid": "s0343V1966", "title": "Head of a Woman", "start": "1884-11-01", "end": "1885-05-30", "display": "November 1884 - May 1885", "location": "http://vangoghmuseum.nl/data/term/1", "current_owner": "http://vocab.getty.edu/ulan/500275558", "link": "https://vangoghworldwide.org/data/artwork/F159"}, {"fnumber": "F216h", "jhnumber": "JH1058", "museumid": "s0200V1962", "title": "Plaster Cast of a Woman's Torso", "start": "1887-02-01", "end": "1887-03-28", "display": "February - March 1887", "location": "http://vangoghmuseum.nl/data/term/2221", "current_owner": "http://vocab.getty.edu/ulan/500275558", "link": "https://vangoghworldwide.org/data/artwork/F216h"}, {"fnumber": "F687", "jhnumber": "JH1782", "museumid": "s0198V1962", "title": "The Reaper (after Millet)", "start": "1889-09-11", "end": "1889-09-20", "display": "mid September 1889", "location": "http://vangoghmuseum.nl/data/term/2229", "current_owner": "http://vocab.getty.edu/ulan/500275558", "link": "https://vangoghworldwide.org/data/artwork/F687"}, {"fnumber": "F216g", "jhnumber": "JH1055", "museumid": "s0199V1962", "title": "Plaster Cast of a Woman's Torso", "start": "1887-02-01", "end": "1887-03-28", "display": "February - March 1887", "location": "http://vangoghmuseum.nl/data/term/2221", "current_owner": "http://vocab.getty.edu/ulan/500275558", "link": "https://vangoghworldwide.org/data/artwork/F216g"}, {"fnumber": "F659", "jhnumber": "JH1850", "museumid": "s0196V1962", "title": "Garden of the Asylum", "start": "1889-11-01", "end": "1889-11-30", "display": "November 1889", "location": "http://vangoghmuseum.nl/data/term/2229", "current_owner": "http://vocab.getty.edu/ulan/500275558", "link": "https://vangoghworldwide.org/data/artwork/F659"}, {"fnumber": "F310", "jhnumber": "JH1274", "museumid": "s0197V1962", "title": "Wheatfield with Partridge", "start": "1887-06-11", "end": "1887-07-20", "display": "mid June - mid July 1887", "location": "http://vangoghmuseum.nl/data/term/2221", "current_owner": "http://vocab.getty.edu/ulan/500275558", "link": "https://vangoghworldwide.org/data/artwork/F310"}, {"fnumber": "F338", "jhnumber": "JH1237", "museumid": "s0193V1962", "title": "Dish with Citrus Fruit", "start": "1887-02-01", "end": "1887-03-28", "display": "February - March 1887", "location": "http://vangoghmuseum.nl/data/term/2221", "current_owner": "http://vocab.getty.edu/ulan/500275558", "link": "https://vangoghworldwide.org/data/artwork/F338"}, {"fnumber": "F816", "jhnumber": "JH2113", "museumid": "s0195V1962", "title": "Tree Roots", "start": "1890-07-21", "end": "1890-07-30", "display": "late July 1890", "location": "http://vangoghmuseum.nl/data/term/59", "current_owner": "http://vocab.getty.edu/ulan/500275558", "link": "https://vangoghworldwide.org/data/artwork/F816"}, {"fnumber": "F603", "jhnumber": "JH1336", "museumid": "s0194V1962", "title": "Grapes", "start": "1887-09-01", "end": "1887-10-30", "display": "September - October 1887", "location": "http://vangoghmuseum.nl/data/term/2221", "current_owner": "http://vocab.getty.edu/ulan/500275558", "link": "https://vangoghworldwide.org/data/artwork/F603"}, {"fnumber": "F610", "jhnumber": "JH1702", "museumid": "s0189V1962", "title": "Giant Peacock Moth", "start": "1889-05-21", "end": "1889-06-10", "display": "late May - early June 1889", "location": "http://vangoghmuseum.nl/data/term/2229", "current_owner": "http://vocab.getty.edu/ulan/500275558", "link": "https://vangoghworldwide.org/data/artwork/F610"}, {"fnumber": "F748", "jhnumber": "JH2013", "museumid": "s0188V1962", "title": "Butterflies and Poppies", "start": "1889-05-01", "end": "1889-06-30", "display": "May - June 1889", "location": "http://vangoghmuseum.nl/data/term/2229", "current_owner": "http://vocab.getty.edu/ulan/500275558", "link": "https://vangoghworldwide.org/data/artwork/F748"}, {"fnumber": "F597", "jhnumber": "JH2011", "museumid": "s0190V1962", "title": "Wild Roses", "start": "1889-05-01", "end": "1889-06-30", "display": "May - June 1889", "location": "http://vangoghmuseum.nl/data/term/2229", "current_owner": "http://vocab.getty.edu/ulan/500275558", "link": "https://vangoghworldwide.org/data/artwork/F597"}, {"fnumber": "F339", "jhnumber": "JH1238", "museumid": "s0186V1962", "title": "Caf\u00e9 Table with Absinthe", "start": "1887-02-01", "end": "1887-03-28", "display": "February - March 1887", "location": "http://vangoghmuseum.nl/data/term/2221", "current_owner": "http://vocab.getty.edu/ulan/500275558", "link": "https://vangoghworldwide.org/data/artwork/F339"}, {"fnumber": "F749", "jhnumber": "JH2012", "museumid": "s0187V1962", "title": "Roses", "start": "1889-05-01", "end": "1889-06-30", "display": "May - June 1889", "location": "http://vangoghmuseum.nl/data/term/2229", "current_owner": "http://vocab.getty.edu/ulan/500275558", "link": "https://vangoghworldwide.org/data/artwork/F749"}, {"fnumber": "F281", "jhnumber": "JH1143", "museumid": "s0185V1962", "title": "Flame Nettle in a Flowerpot", "start": "1886-06-21", "end": "1886-07-20", "display": "late June - mid July 1886", "location": "http://vangoghmuseum.nl/data/term/2221", "current_owner": "http://vocab.getty.edu/ulan/500275558", "link": "https://vangoghworldwide.org/data/artwork/F281"}, {"fnumber": "F243a", "jhnumber": "JH1106", "museumid": "s0182V1962", "title": "Small Bottle with Peonies and Blue Delphiniums", "start": "1886-06-21", "end": "1886-07-20", "display": "late June - mid July 1886", "location": "http://vangoghmuseum.nl/data/term/2221", "current_owner": "http://vocab.getty.edu/ulan/500275558", "link": "https://vangoghworldwide.org/data/artwork/F243a"}, {"fnumber": "F337", "jhnumber": "JH1229", "museumid": "s0183V1962", "title": "Flowerpot with Garlic Chives", "start": "1887-01-01", "end": "1887-02-28", "display": "January - February 1887", "location": "http://vangoghmuseum.nl/data/term/2221", "current_owner": "http://vocab.getty.edu/ulan/500275558", "link": "https://vangoghworldwide.org/data/artwork/F337"}, {"fnumber": "F392", "jhnumber": "JH1361", "museumid": "s0184V1962", "title": "Sprig of Flowering Almond in a Glass", "start": "1888-03-01", "end": "1888-03-10", "display": "early March 1888", "location": "http://vangoghmuseum.nl/data/term/41", "current_owner": "http://vocab.getty.edu/ulan/500275558", "link": "https://vangoghworldwide.org/data/artwork/F392"}, {"fnumber": "F244", "jhnumber": "JH1093", "museumid": "s0180V1962", "title": "Basket of Pansies", "start": "1887-05-01", "end": "1887-05-15", "display": "first half of May 1887", "location": "http://vangoghmuseum.nl/data/term/2221", "current_owner": "http://vocab.getty.edu/ulan/500275558", "link": "https://vangoghworldwide.org/data/artwork/F244"}, {"fnumber": "F334", "jhnumber": "JH1228", "museumid": "s0179V1962", "title": "Basket of Crocus Bulbs", "start": "1887-01-01", "end": "1887-02-28", "display": "January - February 1887", "location": "http://vangoghmuseum.nl/data/term/2221", "current_owner": "http://vocab.getty.edu/ulan/500275558", "link": "https://vangoghworldwide.org/data/artwork/F334"}, {"fnumber": "F335", "jhnumber": "JH1226", "museumid": "s0181V1962", "title": "Three Novels", "start": "1887-01-01", "end": "1887-02-28", "display": "January - February 1887", "location": "http://vangoghmuseum.nl/data/term/2221", "current_owner": "http://vocab.getty.edu/ulan/500275558", "link": "https://vangoghworldwide.org/data/artwork/F335"}, {"fnumber": "F218", "jhnumber": "JH1144", "museumid": "s0178V1962", "title": "Glass with Yellow Roses", "start": "1886-06-21", "end": "1886-07-20", "display": "late June - mid July 1886", "location": "http://vangoghmuseum.nl/data/term/2221", "current_owner": "http://vocab.getty.edu/ulan/500275558", "link": "https://vangoghworldwide.org/data/artwork/F218"}, {"fnumber": "F234", "jhnumber": "JH1168", "museumid": "s0177V1962", "title": "Vase with Chinese Asters and Gladioli", "start": "1886-08-01", "end": "1886-09-20", "display": "August - mid September 1886", "location": "http://vangoghmuseum.nl/data/term/2221", "current_owner": "http://vocab.getty.edu/ulan/500275558", "link": "https://vangoghworldwide.org/data/artwork/F234"}, {"fnumber": "F671", "jhnumber": "JH1891", "museumid": "s0176V1962", "title": "Almond Blossom", "start": "1890-02-01", "end": "1890-02-28", "display": "February 1890", "location": "http://vangoghmuseum.nl/data/term/2229", "current_owner": "http://vocab.getty.edu/ulan/500275558", "link": "https://vangoghworldwide.org/data/artwork/F671"}, {"fnumber": "F632", "jhnumber": "JH1882", "museumid": "s0175V1962", "title": "Snow-Covered Field with a Harrow (after Millet)", "start": "1890-01-16", "end": "1890-01-31", "display": "second half of January 1890", "location": "http://vangoghmuseum.nl/data/term/2229", "current_owner": "http://vocab.getty.edu/ulan/500275558", "link": "https://vangoghworldwide.org/data/artwork/F632"}, {"fnumber": "F700", "jhnumber": "JH1781", "museumid": "s0172V1962", "title": "Peasant Woman Binding Sheaves (after Millet)", "start": "1889-09-11", "end": "1889-09-20", "display": "mid September 1889", "location": "http://vangoghmuseum.nl/data/term/2229", "current_owner": "http://vocab.getty.edu/ulan/500275558", "link": "https://vangoghworldwide.org/data/artwork/F700"}, {"fnumber": "F693", "jhnumber": "JH1785", "museumid": "s0173V1962", "title": "The Sheaf-Binder (after Millet)", "start": "1889-09-11", "end": "1889-09-20", "display": "mid September 1889", "location": "http://vangoghmuseum.nl/data/term/2229", "current_owner": "http://vocab.getty.edu/ulan/500275558", "link": "https://vangoghworldwide.org/data/artwork/F693"}, {"fnumber": "F647", "jhnumber": "JH1834", "museumid": "s0174V1962", "title": "Evening (after Millet)", "start": "1889-10-21", "end": "1889-11-10", "display": "late October - early November 1889", "location": "http://vangoghmuseum.nl/data/term/2229", "current_owner": "http://vocab.getty.edu/ulan/500275558", "link": "https://vangoghworldwide.org/data/artwork/F647"}, {"fnumber": "F670", "jhnumber": "JH1886", "museumid": "s0170V1962", "title": "The Woodcutter (after Millet)", "start": "1889-09-21", "end": "1889-09-30", "display": "late September 1889", "location": "http://vangoghmuseum.nl/data/term/2229", "current_owner": "http://vocab.getty.edu/ulan/500275558", "link": "https://vangoghworldwide.org/data/artwork/F670"}, {"fnumber": "F677", "jhnumber": "JH1972", "museumid": "s0169V1962", "title": "The Raising of Lazarus (after Rembrandt)", "start": "1890-05-01", "end": "1890-05-10", "display": "early May 1890", "location": "http://vangoghmuseum.nl/data/term/2229", "current_owner": "http://vocab.getty.edu/ulan/500275558", "link": "https://vangoghworldwide.org/data/artwork/F677"}, {"fnumber": "F692", "jhnumber": "JH1784", "museumid": "s0171V1962", "title": "Thresher (after Millet)", "start": "1889-09-11", "end": "1889-09-20", "display": "mid September 1889", "location": "http://vangoghmuseum.nl/data/term/2229", "current_owner": "http://vocab.getty.edu/ulan/500275558", "link": "https://vangoghworldwide.org/data/artwork/F692"}, {"fnumber": "F630", "jhnumber": "JH1775", "museumid": "s0168V1962", "title": "Piet\u00e0 (after Delacroix)", "start": "1889-09-11", "end": "1889-09-20", "display": "mid September 1889", "location": "http://vangoghmuseum.nl/data/term/2229", "current_owner": "http://vocab.getty.edu/ulan/500275558", "link": "https://vangoghworldwide.org/data/artwork/F630"}, {"fnumber": "F441", "jhnumber": "JH1641", "museumid": "s0167V1962", "title": "Portrait of Marcelle Roulin", "start": "1888-12-01", "end": "1888-12-30", "display": "December 1888", "location": "http://vangoghmuseum.nl/data/term/41", "current_owner": "http://vocab.getty.edu/ulan/500275558", "link": "https://vangoghworldwide.org/data/artwork/F441"}, {"fnumber": "F538", "jhnumber": "JH1645", "museumid": "s0166V1962", "title": "Portrait of Camille Roulin", "start": "1888-11-01", "end": "1888-12-30", "display": "November - December 1888", "location": "http://vangoghmuseum.nl/data/term/41", "current_owner": "http://vocab.getty.edu/ulan/500275558", "link": "https://vangoghworldwide.org/data/artwork/F538"}, {"fnumber": "F369", "jhnumber": "JH1206", "museumid": "s0165V1962", "title": "Portrait of L\u00e9onie Rose Charbuy-Davy", "start": "1887-03-01", "end": "1887-04-30", "display": "March - April 1887", "location": "http://vangoghmuseum.nl/data/term/2221", "current_owner": "http://vocab.getty.edu/ulan/500275558", "link": "https://vangoghworldwide.org/data/artwork/F369"}, {"fnumber": "F469", "jhnumber": "JH1310", "museumid": "s0164V1962", "title": "Self-Portrait with Straw Hat", "start": "1887-08-01", "end": "1887-09-30", "display": "August - September 1887", "location": "http://vangoghmuseum.nl/data/term/2221", "current_owner": "http://vocab.getty.edu/ulan/500275558", "link": "https://vangoghworldwide.org/data/artwork/F469"}, {"fnumber": "F524", "jhnumber": "JH1565", "museumid": "s0163V1962", "title": "Self-Portrait with Pipe and Straw Hat", "start": "1887-09-01", "end": "1887-10-30", "display": "September - October 1887", "location": "http://vangoghmuseum.nl/data/term/2221", "current_owner": "http://vocab.getty.edu/ulan/500275558", "link": "https://vangoghworldwide.org/data/artwork/F524"}, {"fnumber": "F208a", "jhnumber": "JH1089", "museumid": "s0162V1962", "title": "Self-Portrait with Felt Hat", "start": "1886-12-01", "end": "1887-01-31", "display": "December 1886 - January 1887", "location": "http://vangoghmuseum.nl/data/term/2221", "current_owner": "http://vocab.getty.edu/ulan/500275558", "link": "https://vangoghworldwide.org/data/artwork/F208a"}, {"fnumber": "F263a", "jhnumber": "JH1199", "museumid": "s0161V1962", "title": "Self-Portrait with Glass", "start": "1887-01-01", "end": "1887-01-31", "display": "January 1887", "location": "http://vangoghmuseum.nl/data/term/2221", "current_owner": "http://vocab.getty.edu/ulan/500275558", "link": "https://vangoghworldwide.org/data/artwork/F263a"}, {"fnumber": "F181", "jhnumber": "JH1090", "museumid": "s0160V1962", "title": "Self-Portrait as a Painter", "start": "1886-09-01", "end": "1886-11-30", "display": "September - November 1886", "location": "http://vangoghmuseum.nl/data/term/2221", "current_owner": "http://vocab.getty.edu/ulan/500275558", "link": "https://vangoghworldwide.org/data/artwork/F181"}, {"fnumber": "F208", "jhnumber": "JH1195", "museumid": "s0159V1962", "title": "Self-Portrait", "start": "1886-03-01", "end": "1886-06-30", "display": "March - June 1886", "location": "http://vangoghmuseum.nl/data/term/2221", "current_owner": "http://vocab.getty.edu/ulan/500275558", "link": "https://vangoghworldwide.org/data/artwork/F208"}, {"fnumber": "F180", "jhnumber": "JH1194", "museumid": "s0158V1962", "title": "Self-Portrait with Pipe", "start": "1886-09-01", "end": "1886-11-30", "display": "September - November 1886", "location": "http://vangoghmuseum.nl/data/term/2221", "current_owner": "http://vocab.getty.edu/ulan/500275558", "link": "https://vangoghworldwide.org/data/artwork/F180"}, {"fnumber": "F267", "jhnumber": "JH1224", "museumid": "s0155V1962", "title": "Self-Portrait", "start": "1887-03-01", "end": "1887-06-30", "display": "March - June 1887", "location": "http://vangoghmuseum.nl/data/term/2221", "current_owner": "http://vocab.getty.edu/ulan/500275558", "link": "https://vangoghworldwide.org/data/artwork/F267"}, {"fnumber": "F294", "jhnumber": "JH1209", "museumid": "s0157V1962", "title": "Self-Portrait or Portrait of Theo van Gogh", "start": "1887-06-01", "end": "1887-08-31", "display": "summer 1887", "location": "http://vangoghmuseum.nl/data/term/2221", "current_owner": "http://vocab.getty.edu/ulan/500275558", "link": "https://vangoghworldwide.org/data/artwork/F294"}, {"fnumber": "F296", "jhnumber": "JH1210", "museumid": "s0156V1962", "title": "Self-Portrait", "start": "1887-06-01", "end": "1887-08-31", "display": "summer 1887", "location": "http://vangoghmuseum.nl/data/term/2221", "current_owner": "http://vocab.getty.edu/ulan/500275558", "link": "https://vangoghworldwide.org/data/artwork/F296"}, {"fnumber": "F107", "jhnumber": "JH933", "museumid": "s0154V1962", "title": "Baskets of Potatoes", "start": "1885-09-01", "end": "1885-09-30", "display": "September 1885", "location": "http://vangoghmuseum.nl/data/term/1", "current_owner": "http://vocab.getty.edu/ulan/500275558", "link": "https://vangoghworldwide.org/data/artwork/F107"}, {"fnumber": "F116", "jhnumber": "JH934", "museumid": "s0152V1962", "title": "Basket of Potatoes", "start": "1885-09-01", "end": "1885-09-30", "display": "September 1885", "location": "http://vangoghmuseum.nl/data/term/1", "current_owner": "http://vocab.getty.edu/ulan/500275558", "link": "https://vangoghworldwide.org/data/artwork/F116"}, {"fnumber": "F100", "jhnumber": "JH931", "museumid": "s0153V1962", "title": "Basket of Potatoes", "start": "1885-09-01", "end": "1885-09-30", "display": "September 1885", "location": "http://vangoghmuseum.nl/data/term/1", "current_owner": "http://vocab.getty.edu/ulan/500275558", "link": "https://vangoghworldwide.org/data/artwork/F100"}, {"fnumber": "F99", "jhnumber": "JH930", "museumid": "s0151V1962", "title": "Basket of Apples", "start": "1885-09-01", "end": "1885-09-30", "display": "September 1885", "location": "http://vangoghmuseum.nl/data/term/1", "current_owner": "http://vocab.getty.edu/ulan/500275558", "link": "https://vangoghworldwide.org/data/artwork/F99"}, {"fnumber": "F101", "jhnumber": "JH927", "museumid": "s0150V1962", "title": "Basket of Apples", "start": "1885-09-01", "end": "1885-09-30", "display": "September 1885", "location": "http://vangoghmuseum.nl/data/term/1", "current_owner": "http://vocab.getty.edu/ulan/500275558", "link": "https://vangoghworldwide.org/data/artwork/F101"}, {"fnumber": "F779", "jhnumber": "JH2117", "museumid": "s0149V1962", "title": "Wheatfield with Crows", "start": "1890-07-01", "end": "1890-07-15", "display": "first half of July 1890", "location": "http://vangoghmuseum.nl/data/term/59", "current_owner": "http://vocab.getty.edu/ulan/500275558", "link": "https://vangoghworldwide.org/data/artwork/F779"}, {"fnumber": "F716", "jhnumber": "JH1878", "museumid": "s0148V1962", "title": "Olive Trees on a Hillside", "start": "1889-11-01", "end": "1889-12-30", "display": "November - December 1889", "location": "http://vangoghmuseum.nl/data/term/2229", "current_owner": "http://vocab.getty.edu/ulan/500275558", "link": "https://vangoghworldwide.org/data/artwork/F716"}, {"fnumber": "F621", "jhnumber": "JH1888", "museumid": "s0147V1962", "title": "Cypresses and Two Women", "start": "1890-02-01", "end": "1890-02-28", "display": "February 1890", "location": "http://vangoghmuseum.nl/data/term/2229", "current_owner": "http://vocab.getty.edu/ulan/500275558", "link": "https://vangoghworldwide.org/data/artwork/F621"}, {"fnumber": "F248a", "jhnumber": "JH1148", "museumid": "s0144V1962", "title": "Vase with Gladioli and Chinese Asters", "start": "1886-08-01", "end": "1886-09-20", "display": "August - mid September 1886", "location": "http://vangoghmuseum.nl/data/term/2221", "current_owner": "http://vocab.getty.edu/ulan/500275558", "link": "https://vangoghworldwide.org/data/artwork/F248a"}, {"fnumber": "F411", "jhnumber": "JH1476", "museumid": "s0146V1962", "title": "Wheatfield", "start": "1888-06-01", "end": "1888-06-30", "display": "June 1888", "location": "http://vangoghmuseum.nl/data/term/41", "current_owner": "http://vocab.getty.edu/ulan/500275558", "link": "https://vangoghworldwide.org/data/artwork/F411"}, {"fnumber": "F390", "jhnumber": "JH1357", "museumid": "s0145V1962", "title": "An Old Woman of Arles", "start": "1888-02-19", "end": "1888-02-26", "display": "circa 21-24 February 1888", "location": "http://vangoghmuseum.nl/data/term/41", "current_owner": "http://vocab.getty.edu/ulan/500275558", "link": "https://vangoghworldwide.org/data/artwork/F390"}, {"fnumber": "F207a", "jhnumber": "JH1204", "museumid": "s0143V1962", "title": "Portrait of a Woman", "start": "1885-12-11", "end": "1885-12-30", "display": "mid - late December 1885", "location": "http://vangoghmuseum.nl/data/term/2269", "current_owner": "http://vocab.getty.edu/ulan/500275558", "link": "https://vangoghworldwide.org/data/artwork/F207a"}, {"fnumber": "F260", "jhnumber": "JH970", "museumid": "s0142V1962", "title": "Houses Seen from the Back", "start": "1885-12-09", "end": "1886-02-28", "display": "9 December 1885 - late February 1886", "location": "http://vangoghmuseum.nl/data/term/2269", "current_owner": "http://vocab.getty.edu/ulan/500275558", "link": "https://vangoghworldwide.org/data/artwork/F260"}, {"fnumber": "F130", "jhnumber": "JH692", "museumid": "s0139V1962", "title": "Head of a Woman (Gordina de Groot)", "start": "1885-03-01", "end": "1885-03-28", "display": "March 1885", "location": "http://vangoghmuseum.nl/data/term/1", "current_owner": "http://vocab.getty.edu/ulan/500275558", "link": "https://vangoghworldwide.org/data/artwork/F130"}, {"fnumber": "F122", "jhnumber": "JH522", "museumid": "s0141M1977", "title": "Avenue of Poplars in Autumn", "start": "1884-10-21", "end": "1884-10-30", "display": "late October 1884", "location": "http://vangoghmuseum.nl/data/term/1", "current_owner": "http://vocab.getty.edu/ulan/500275558", "link": "https://vangoghworldwide.org/data/artwork/F122"}, {"fnumber": "F182", "jhnumber": "JH948", "museumid": "s0140V1962", "title": "The Vicarage at Nuenen", "start": "1885-09-01", "end": "1885-10-10", "display": "September - early October 1885", "location": "http://vangoghmuseum.nl/data/term/1", "current_owner": "http://vocab.getty.edu/ulan/500275558", "link": "https://vangoghworldwide.org/data/artwork/F182"}, {"fnumber": "F177a", "jhnumber": "JH1192", "museumid": "s0136V1973", "title": "Flying Fox", "start": "1884-10-01", "end": "1884-11-30", "display": "October - November 1884", "location": "http://vangoghmuseum.nl/data/term/1", "current_owner": "http://vocab.getty.edu/ulan/500275558", "link": "https://vangoghworldwide.org/data/artwork/F177a"}, {"fnumber": "F53", "jhnumber": "JH538", "museumid": "s0138V1962", "title": "Still Life with Earthenware and Bottles", "start": "1885-09-01", "end": "1885-10-20", "display": "September - mid October 1885", "location": "http://vangoghmuseum.nl/data/term/1", "current_owner": "http://vocab.getty.edu/ulan/500275558", "link": "https://vangoghworldwide.org/data/artwork/F53"}, {"fnumber": "F1", "jhnumber": "JH81", "museumid": "s0137V1962", "title": "Still Life with Cabbage and Clogs", "start": "1881-11-21", "end": "1881-12-20", "display": "late November - mid December 1881", "location": "http://vangoghmuseum.nl/data/term/3554", "current_owner": "http://vocab.getty.edu/ulan/500275558", "link": "https://vangoghworldwide.org/data/artwork/F1"}, {"fnumber": "F77v", "jhnumber": "JH1304", "museumid": "s0135V1962v", "title": "Self-Portrait", "start": "1887-07-11", "end": "1887-08-31", "display": "mid July - August 1887", "location": "http://vangoghmuseum.nl/data/term/2221", "current_owner": "http://vocab.getty.edu/ulan/500275558", "link": "https://vangoghworldwide.org/data/artwork/F77v"}, {"fnumber": "F321", "jhnumber": "JH1311", "museumid": "s0134V1962", "title": "Exterior of a Restaurant in Asni\u00e8res", "start": "1887-05-11", "end": "1887-06-20", "display": "mid May - mid June 1887", "location": "http://vangoghmuseum.nl/data/term/2221", "current_owner": "http://vocab.getty.edu/ulan/500275558", "link": "https://vangoghworldwide.org/data/artwork/F321"}, {"fnumber": "F77r", "jhnumber": "JH686", "museumid": "s0135V1962r", "title": "Study for 'The Potato Eaters'", "start": "1885-04-01", "end": "1885-04-10", "display": "early April 1885", "location": "http://vangoghmuseum.nl/data/term/1", "current_owner": "http://vocab.getty.edu/ulan/500275558", "link": "https://vangoghworldwide.org/data/artwork/F77r"}, {"fnumber": "F254", "jhnumber": "JH1342", "museumid": "s0131V1962", "title": "Apples", "start": "1887-09-01", "end": "1887-10-30", "display": "September - October 1887", "location": "http://vangoghmuseum.nl/data/term/2221", "current_owner": "http://vocab.getty.edu/ulan/500275558", "link": "https://vangoghworldwide.org/data/artwork/F254"}, {"fnumber": "F70a", "jhnumber": "JH716", "museumid": "s0132V1962", "title": "Head of a Woman", "start": "1885-03-01", "end": "1885-03-28", "display": "March 1885", "location": "http://vangoghmuseum.nl/data/term/1", "current_owner": "http://vocab.getty.edu/ulan/500275558", "link": "https://vangoghworldwide.org/data/artwork/F70a"}, {"fnumber": "F266a", "jhnumber": "JH1223", "museumid": "s0133M1970", "title": "Sunset in Montmartre", "start": "1887-02-21", "end": "1887-03-10", "display": "late February - early March 1887", "location": "http://vangoghmuseum.nl/data/term/2221", "current_owner": "http://vocab.getty.edu/ulan/500275558", "link": "https://vangoghworldwide.org/data/artwork/F266a"}, {"fnumber": "F19", "jhnumber": "JH409", "museumid": "s0129V1962", "title": "Women on the Peat Moor", "start": "1883-10-01", "end": "1883-10-30", "display": "October 1883", "location": "http://vangoghmuseum.nl/data/term/3551", "current_owner": "http://vocab.getty.edu/ulan/500275558", "link": "https://vangoghworldwide.org/data/artwork/F19"}, {"fnumber": "F297a", "jhnumber": "JH1347", "museumid": "s0128V1962", "title": "Skull", "start": "1887-05-01", "end": "1887-05-15", "display": "first half of May 1887", "location": "http://vangoghmuseum.nl/data/term/2221", "current_owner": "http://vocab.getty.edu/ulan/500275558", "link": "https://vangoghworldwide.org/data/artwork/F297a"}, {"fnumber": "F22", "jhnumber": "JH421", "museumid": "s0130V1962", "title": "Farm with Stacks of Peat", "start": "1883-10-13", "end": "1883-10-17", "display": "circa 15 October 1883", "location": "http://vangoghmuseum.nl/data/term/3551", "current_owner": "http://vocab.getty.edu/ulan/500275558", "link": "https://vangoghworldwide.org/data/artwork/F22"}, {"fnumber": "F331", "jhnumber": "JH1235", "museumid": "s0127V1962", "title": "Shoes", "start": "1887-01-01", "end": "1887-02-28", "display": "January - February 1887", "location": "http://vangoghmuseum.nl/data/term/2221", "current_owner": "http://vocab.getty.edu/ulan/500275558", "link": "https://vangoghworldwide.org/data/artwork/F331"}, {"fnumber": "F270a", "jhnumber": "JH1272", "museumid": "s0126V1962", "title": "Horse Chestnut Tree in Blossom", "start": "1887-05-11", "end": "1887-05-20", "display": "mid May 1887", "location": "http://vangoghmuseum.nl/data/term/2221", "current_owner": "http://vocab.getty.edu/ulan/500275558", "link": "https://vangoghworldwide.org/data/artwork/F270a"}, {"fnumber": "F289", "jhnumber": "JH1203", "museumid": "s0125V1962", "title": "Portrait of Etienne-Lucien Martin", "start": "1887-11-01", "end": "1887-11-30", "display": "November 1887", "location": "http://vangoghmuseum.nl/data/term/2221", "current_owner": "http://vocab.getty.edu/ulan/500275558", "link": "https://vangoghworldwide.org/data/artwork/F289"}, {"fnumber": "F256", "jhnumber": "JH1169", "museumid": "s0122V1962", "title": "Prawns and Mussels", "start": "1886-09-01", "end": "1886-11-30", "display": "September - November 1886", "location": "http://vangoghmuseum.nl/data/term/2221", "current_owner": "http://vocab.getty.edu/ulan/500275558", "link": "https://vangoghworldwide.org/data/artwork/F256"}, {"fnumber": "F297", "jhnumber": "JH1346", "museumid": "s0123V1962", "title": "Skull", "start": "1887-05-01", "end": "1887-05-15", "display": "first half of May 1887", "location": "http://vangoghmuseum.nl/data/term/2221", "current_owner": "http://vocab.getty.edu/ulan/500275558", "link": "https://vangoghworldwide.org/data/artwork/F297"}, {"fnumber": "F605", "jhnumber": "JH1663", "museumid": "s0124V1962", "title": "A Crab on its Back", "start": "1887-08-01", "end": "1887-09-30", "display": "August - September 1887", "location": "http://vangoghmuseum.nl/data/term/2221", "current_owner": "http://vocab.getty.edu/ulan/500275558", "link": "https://vangoghworldwide.org/data/artwork/F605"}, {"fnumber": "F607", "jhnumber": "JH1364", "museumid": "s0120V1962", "title": "A Pair of Leather Clogs", "start": "1889-09-01", "end": "1889-10-30", "display": "September - October 1889", "location": "http://vangoghmuseum.nl/data/term/2229", "current_owner": "http://vocab.getty.edu/ulan/500275558", "link": "https://vangoghworldwide.org/data/artwork/F607"}, {"fnumber": "F377", "jhnumber": "JH1328", "museumid": "s0121V1962", "title": "Sunflowers Gone to Seed", "start": "1887-08-11", "end": "1887-09-20", "display": "mid August - mid September 1887", "location": "http://vangoghmuseum.nl/data/term/2221", "current_owner": "http://vocab.getty.edu/ulan/500275558", "link": "https://vangoghworldwide.org/data/artwork/F377"}, {"fnumber": "F645", "jhnumber": "JH1803", "museumid": "s0118V1962", "title": "Ravine with a Small Stream", "start": "1889-10-01", "end": "1889-10-30", "display": "October 1889", "location": "http://vangoghmuseum.nl/data/term/2229", "current_owner": "http://vocab.getty.edu/ulan/500275558", "link": "https://vangoghworldwide.org/data/artwork/F645"}, {"fnumber": "F389", "jhnumber": "JH1359", "museumid": "s0119V1962", "title": "View of a Butcher's Shop", "start": "1888-02-22", "end": "1888-02-26", "display": "circa 24 February 1888", "location": "http://vangoghmuseum.nl/data/term/41", "current_owner": "http://vocab.getty.edu/ulan/500275558", "link": "https://vangoghworldwide.org/data/artwork/F389"}, {"fnumber": "F415", "jhnumber": "JH1452", "museumid": "s0117V1962", "title": "Seascape near Les Saintes-Maries-de-la-Mer", "start": "1888-06-01", "end": "1888-06-10", "display": "early June 1888", "location": "http://vangoghmuseum.nl/data/term/41", "current_owner": "http://vocab.getty.edu/ulan/500275558", "link": "https://vangoghworldwide.org/data/artwork/F415"}, {"fnumber": "F371", "jhnumber": "JH1296", "museumid": "s0115V1962", "title": "Flowering Plum Orchard (after Hiroshige)", "start": "1887-10-01", "end": "1887-11-30", "display": "October - November 1887", "location": "http://vangoghmuseum.nl/data/term/2221", "current_owner": "http://vocab.getty.edu/ulan/500275558", "link": "https://vangoghworldwide.org/data/artwork/F371"}, {"fnumber": "F373", "jhnumber": "JH1298", "museumid": "s0116V1962", "title": "Courtesan (after Eisen)", "start": "1887-10-01", "end": "1887-11-30", "display": "October - November 1887", "location": "http://vangoghmuseum.nl/data/term/2221", "current_owner": "http://vocab.getty.edu/ulan/500275558", "link": "https://vangoghworldwide.org/data/artwork/F373"}, {"fnumber": "F372", "jhnumber": "JH1297", "museumid": "s0114V1962", "title": "Bridge in the Rain (after Hiroshige)", "start": "1887-10-01", "end": "1887-11-30", "display": "October - November 1887", "location": "http://vangoghmuseum.nl/data/term/2221", "current_owner": "http://vocab.getty.edu/ulan/500275558", "link": "https://vangoghworldwide.org/data/artwork/F372"}, {"fnumber": "F532", "jhnumber": "JH1650", "museumid": "s0113V1962", "title": "Portrait of a One-Eyed Man", "start": "1889-09-01", "end": "1889-10-30", "display": "September - October 1889", "location": "http://vangoghmuseum.nl/data/term/2229", "current_owner": "http://vocab.getty.edu/ulan/500275558", "link": "https://vangoghworldwide.org/data/artwork/F532"}, {"fnumber": "F745", "jhnumber": "JH1764", "museumid": "s0111V1962", "title": "Undergrowth", "start": "1889-07-01", "end": "1889-07-15", "display": "first half of July 1889", "location": "http://vangoghmuseum.nl/data/term/2229", "current_owner": "http://vocab.getty.edu/ulan/500275558", "link": "https://vangoghworldwide.org/data/artwork/F745"}, {"fnumber": "F764a", "jhnumber": "JH2046", "museumid": "s0109V1962", "title": "Vase of Flowers", "start": "1890-06-01", "end": "1890-06-30", "display": "June 1890", "location": "http://vangoghmuseum.nl/data/term/59", "current_owner": "http://vocab.getty.edu/ulan/500275558", "link": "https://vangoghworldwide.org/data/artwork/F764a"}, {"fnumber": "F402", "jhnumber": "JH1677", "museumid": "s0110V1962", "title": "Garden with Butterflies", "start": "1890-03-01", "end": "1890-05-31", "display": "spring 1890", "location": "http://vangoghmuseum.nl/data/term/2229", "current_owner": "http://vocab.getty.edu/ulan/500275558", "link": "https://vangoghworldwide.org/data/artwork/F402"}, {"fnumber": "F675", "jhnumber": "JH1921", "museumid": "s0112V1962", "title": "Reminiscence of Brabant", "start": "1890-03-01", "end": "1890-04-30", "display": "March - April 1890", "location": "http://vangoghmuseum.nl/data/term/2229", "current_owner": "http://vocab.getty.edu/ulan/500275558", "link": "https://vangoghworldwide.org/data/artwork/F675"}, {"fnumber": "F770", "jhnumber": "JH2040", "museumid": "s0107V1962", "title": "Landscape at Twilight", "start": "1890-06-21", "end": "1890-06-30", "display": "late June 1890", "location": "http://vangoghmuseum.nl/data/term/59", "current_owner": "http://vocab.getty.edu/ulan/500275558", "link": "https://vangoghworldwide.org/data/artwork/F770"}, {"fnumber": "F806", "jhnumber": "JH2017", "museumid": "s0108V1962", "title": "Farmhouse", "start": "1890-05-01", "end": "1890-06-30", "display": "May - June 1890", "location": "http://vangoghmuseum.nl/data/term/59", "current_owner": "http://vocab.getty.edu/ulan/500275558", "link": "https://vangoghworldwide.org/data/artwork/F806"}, {"fnumber": "F778", "jhnumber": "JH2097", "museumid": "s0106V1962", "title": "Wheatfield under Thunderclouds", "start": "1890-07-01", "end": "1890-07-15", "display": "first half of July 1890", "location": "http://vangoghmuseum.nl/data/term/59", "current_owner": "http://vocab.getty.edu/ulan/500275558", "link": "https://vangoghworldwide.org/data/artwork/F778"}, {"fnumber": "F799", "jhnumber": "JH2004", "museumid": "s0105V1962", "title": "View of Auvers-sur-Oise", "start": "1890-05-01", "end": "1890-06-30", "display": "May - June 1890", "location": "http://vangoghmuseum.nl/data/term/59", "current_owner": "http://vocab.getty.edu/ulan/500275558", "link": "https://vangoghworldwide.org/data/artwork/F799"}, {"fnumber": "F216e", "jhnumber": "JH1078", "museumid": "s0103V1962", "title": "Male Torso", "start": "1886-06-11", "end": "1886-06-20", "display": "mid June 1886", "location": "http://vangoghmuseum.nl/data/term/2221", "current_owner": "http://vocab.getty.edu/ulan/500275558", "link": "https://vangoghworldwide.org/data/artwork/F216e"}, {"fnumber": "F216f", "jhnumber": "JH1076", "museumid": "s0102V1962", "title": "Kneeling Ecorch\u00e9", "start": "1886-06-11", "end": "1886-06-20", "display": "mid June 1886", "location": "http://vangoghmuseum.nl/data/term/2221", "current_owner": "http://vocab.getty.edu/ulan/500275558", "link": "https://vangoghworldwide.org/data/artwork/F216f"}, {"fnumber": "F765", "jhnumber": "JH2029", "museumid": "s0104V1962", "title": "Daubigny's Garden", "start": "1890-06-11", "end": "1890-06-20", "display": "mid June 1890", "location": "http://vangoghmuseum.nl/data/term/59", "current_owner": "http://vocab.getty.edu/ulan/500275558", "link": "https://vangoghworldwide.org/data/artwork/F765"}, {"fnumber": "F275", "jhnumber": "JH1278", "museumid": "s0098V1962", "title": "Square Saint-Pierre at Sunset", "start": "1887-05-01", "end": "1887-05-15", "display": "first half of May 1887", "location": "http://vangoghmuseum.nl/data/term/2221", "current_owner": "http://vocab.getty.edu/ulan/500275558", "link": "https://vangoghworldwide.org/data/artwork/F275"}, {"fnumber": "F739", "jhnumber": "JH1876", "museumid": "s0099V1962", "title": "Landscape with Rabbits", "start": "1889-12-01", "end": "1889-12-30", "display": "December 1889", "location": "http://vangoghmuseum.nl/data/term/2229", "current_owner": "http://vocab.getty.edu/ulan/500275558", "link": "https://vangoghworldwide.org/data/artwork/F739"}, {"fnumber": "F216d", "jhnumber": "JH1071", "museumid": "s0101V1962", "title": "Torso of Venus", "start": "1886-06-11", "end": "1886-06-20", "display": "mid June 1886", "location": "http://vangoghmuseum.nl/data/term/2221", "current_owner": "http://vocab.getty.edu/ulan/500275558", "link": "https://vangoghworldwide.org/data/artwork/F216d"}, {"fnumber": "F28", "jhnumber": "JH1191", "museumid": "s0100V1962", "title": "Kingfisher by the Waterside", "start": "1887-07-01", "end": "1887-08-31", "display": "July - August 1887", "location": "http://vangoghmuseum.nl/data/term/2221", "current_owner": "http://vocab.getty.edu/ulan/500275558", "link": "https://vangoghworldwide.org/data/artwork/F28"}, {"fnumber": "F269v", "jhnumber": "JH1301", "museumid": "s0097V1962v", "title": "Self-Portrait", "start": "1887-07-11", "end": "1887-08-31", "display": "mid July - August 1887", "location": "http://vangoghmuseum.nl/data/term/2221", "current_owner": "http://vocab.getty.edu/ulan/500275558", "link": "https://vangoghworldwide.org/data/artwork/F269v"}, {"fnumber": "F269r", "jhnumber": "JH725", "museumid": "s0097V1962r", "title": "Head of a Woman", "start": "1885-03-01", "end": "1885-05-30", "display": "March - May 1885", "location": "http://vangoghmuseum.nl/data/term/1", "current_owner": "http://vocab.getty.edu/ulan/500275558", "link": "https://vangoghworldwide.org/data/artwork/F269r"}, {"fnumber": "F231", "jhnumber": "JH1099", "museumid": "s0095V1962", "title": "View from Vincent's Studio", "start": "1886-06-01", "end": "1886-06-10", "display": "early June 1886", "location": "http://vangoghmuseum.nl/data/term/2221", "current_owner": "http://vocab.getty.edu/ulan/500275558", "link": "https://vangoghworldwide.org/data/artwork/F231"}, {"fnumber": "F49", "jhnumber": "JH534", "museumid": "s0096V1962", "title": "Beer Tankards", "start": "1885-09-01", "end": "1885-10-20", "display": "September - mid October 1885", "location": "http://vangoghmuseum.nl/data/term/1", "current_owner": "http://vocab.getty.edu/ulan/500275558", "link": "https://vangoghworldwide.org/data/artwork/F49"}, {"fnumber": "F232", "jhnumber": "JH1113", "museumid": "s0092V1962", "title": "Path in Montmartre", "start": "1886-04-21", "end": "1886-05-10", "display": "late April - early May 1886", "location": "http://vangoghmuseum.nl/data/term/2221", "current_owner": "http://vocab.getty.edu/ulan/500275558", "link": "https://vangoghworldwide.org/data/artwork/F232"}, {"fnumber": "F292", "jhnumber": "JH1219", "museumid": "s0094V1962", "title": "Boulevard de Clichy", "start": "1887-03-01", "end": "1887-04-20", "display": "March - mid April 1887", "location": "http://vangoghmuseum.nl/data/term/2221", "current_owner": "http://vocab.getty.edu/ulan/500275558", "link": "https://vangoghworldwide.org/data/artwork/F292"}, {"fnumber": "F215b", "jhnumber": "JH1205", "museumid": "s0093V1962", "title": "Portrait of Agostina Segatori", "start": "1887-01-01", "end": "1887-02-28", "display": "January - February 1887", "location": "http://vangoghmuseum.nl/data/term/2221", "current_owner": "http://vocab.getty.edu/ulan/500275558", "link": "https://vangoghworldwide.org/data/artwork/F215b"}, {"fnumber": "F216b", "jhnumber": "JH1060", "museumid": "s0089V1962", "title": "Torso of Venus", "start": "1886-06-11", "end": "1886-06-20", "display": "mid June 1886", "location": "http://vangoghmuseum.nl/data/term/2221", "current_owner": "http://vocab.getty.edu/ulan/500275558", "link": "https://vangoghworldwide.org/data/artwork/F216b"}, {"fnumber": "F215", "jhnumber": "JH1045", "museumid": "s0090V1962", "title": "Nude Girl, Seated", "start": "1886-04-01", "end": "1886-06-10", "display": "April - early June 1886", "location": "http://vangoghmuseum.nl/data/term/2221", "current_owner": "http://vocab.getty.edu/ulan/500275558", "link": "https://vangoghworldwide.org/data/artwork/F215"}, {"fnumber": "F215c", "jhnumber": null, "museumid": "s0091V1962", "title": "Portrait of a Woman", "start": "1886-03-01", "end": "1886-06-30", "display": "March - June 1886", "location": "http://vangoghmuseum.nl/data/term/2221", "current_owner": "http://vocab.getty.edu/ulan/500275558", "link": "https://vangoghworldwide.org/data/artwork/F215c"}, {"fnumber": "F83", "jhnumber": "JH777", "museumid": "s0087V1962", "title": "The Cottage", "start": "1885-05-21", "end": "1885-05-30", "display": "late May 1885", "location": "http://vangoghmuseum.nl/data/term/1", "current_owner": "http://vocab.getty.edu/ulan/500275558", "link": "https://vangoghworldwide.org/data/artwork/F83"}, {"fnumber": "F767", "jhnumber": "JH2034", "museumid": "s0088V1962", "title": "Ears of Wheat", "start": "1890-06-01", "end": "1890-06-30", "display": "June 1890", "location": "http://vangoghmuseum.nl/data/term/59", "current_owner": "http://vocab.getty.edu/ulan/500275558", "link": "https://vangoghworldwide.org/data/artwork/F767"}, {"fnumber": "F211", "jhnumber": "JH973", "museumid": "s0085V1962", "title": "The De Ruijterkade in Amsterdam", "start": "1885-10-08", "end": "1885-10-08", "display": "8 October 1885", "location": "http://vangoghmuseum.nl/data/term/2235", "current_owner": "http://vocab.getty.edu/ulan/500275558", "link": "https://vangoghworldwide.org/data/artwork/F211"}, {"fnumber": "F69", "jhnumber": "JH724", "museumid": "s0084V1962", "title": "Head of a Woman", "start": "1885-03-01", "end": "1885-05-30", "display": "March - May 1885", "location": "http://vangoghmuseum.nl/data/term/1", "current_owner": "http://vocab.getty.edu/ulan/500275558", "link": "https://vangoghworldwide.org/data/artwork/F69"}, {"fnumber": "F304", "jhnumber": "JH1326", "museumid": "s0086V1962", "title": "The Bridge at Courbevoie", "start": "1887-05-11", "end": "1887-07-30", "display": "mid May - late July 1887", "location": "http://vangoghmuseum.nl/data/term/2221", "current_owner": "http://vocab.getty.edu/ulan/500275558", "link": "https://vangoghworldwide.org/data/artwork/F304"}, {"fnumber": "F212", "jhnumber": "JH999", "museumid": "s0083V1962", "title": "Head of a Skeleton with a Burning Cigarette", "start": "1886-01-18", "end": "1886-02-10", "display": "18 January 1886 - early February 1886", "location": "http://vangoghmuseum.nl/data/term/2269", "current_owner": "http://vocab.getty.edu/ulan/500275558", "link": "https://vangoghworldwide.org/data/artwork/F212"}, {"fnumber": "F374", "jhnumber": "JH1338", "museumid": "s0082V1962", "title": "Red Cabbages and Garlic", "start": "1887-10-01", "end": "1887-11-30", "display": "October - November 1887", "location": "http://vangoghmuseum.nl/data/term/2221", "current_owner": "http://vocab.getty.edu/ulan/500275558", "link": "https://vangoghworldwide.org/data/artwork/F374"}, {"fnumber": "F703", "jhnumber": "JH1832", "museumid": "s0081V1962", "title": "Portrait of a Man", "start": "1889-10-01", "end": "1889-10-30", "display": "October 1889", "location": "http://vangoghmuseum.nl/data/term/2229", "current_owner": "http://vocab.getty.edu/ulan/500275558", "link": "https://vangoghworldwide.org/data/artwork/F703"}, {"fnumber": "F309", "jhnumber": "JH1315", "museumid": "s0080V1962", "title": "Path in the Woods", "start": "1887-05-11", "end": "1887-07-20", "display": "mid May - mid July 1887", "location": "http://vangoghmuseum.nl/data/term/2221", "current_owner": "http://vocab.getty.edu/ulan/500275558", "link": "https://vangoghworldwide.org/data/artwork/F309"}, {"fnumber": "F307", "jhnumber": "JH1318", "museumid": "s0078V1962", "title": "Trees", "start": "1887-07-16", "end": "1887-07-30", "display": "second half of July 1887", "location": "http://vangoghmuseum.nl/data/term/2221", "current_owner": "http://vocab.getty.edu/ulan/500275558", "link": "https://vangoghworldwide.org/data/artwork/F307"}, {"fnumber": "F293", "jhnumber": "JH1269", "museumid": "s0077V1962", "title": "Bank of the Seine", "start": "1887-05-11", "end": "1887-07-30", "display": "mid May - late July 1887", "location": "http://vangoghmuseum.nl/data/term/2221", "current_owner": "http://vocab.getty.edu/ulan/500275558", "link": "https://vangoghworldwide.org/data/artwork/F293"}, {"fnumber": "F308", "jhnumber": "JH1313", "museumid": "s0079V1962", "title": "Undergrowth", "start": "1887-07-16", "end": "1887-07-30", "display": "second half of July 1887", "location": "http://vangoghmuseum.nl/data/term/2221", "current_owner": "http://vocab.getty.edu/ulan/500275558", "link": "https://vangoghworldwide.org/data/artwork/F308"}, {"fnumber": "F216i", "jhnumber": "JH1072", "museumid": "s0075V1962", "title": "Plaster Cast of a Woman's Torso", "start": "1887-02-01", "end": "1887-03-28", "display": "February - March 1887", "location": "http://vangoghmuseum.nl/data/term/2221", "current_owner": "http://vocab.getty.edu/ulan/500275558", "link": "https://vangoghworldwide.org/data/artwork/F216i"}, {"fnumber": "F215d", "jhnumber": null, "museumid": "s0074V1962", "title": "Portrait of a Woman", "start": "1886-03-01", "end": "1886-06-30", "display": "March - June 1886", "location": "http://vangoghmuseum.nl/data/term/2221", "current_owner": "http://vocab.getty.edu/ulan/500275558", "link": "https://vangoghworldwide.org/data/artwork/F215d"}, {"fnumber": "F36", "jhnumber": "JH698", "museumid": "s0073V1962", "title": "Woman Winding Yarn", "start": "1885-03-01", "end": "1885-03-28", "display": "March 1885", "location": "http://vangoghmuseum.nl/data/term/1", "current_owner": "http://vocab.getty.edu/ulan/500275558", "link": "https://vangoghworldwide.org/data/artwork/F36"}, {"fnumber": "F156", "jhnumber": "JH569", "museumid": "s0072V1962", "title": "Head of a Woman", "start": "1884-11-01", "end": "1885-01-31", "display": "November 1884 - January 1885", "location": "http://vangoghmuseum.nl/data/term/1", "current_owner": "http://vocab.getty.edu/ulan/500275558", "link": "https://vangoghworldwide.org/data/artwork/F156"}, {"fnumber": "F109r", "jhnumber": "JH942", "museumid": "s0071V1962r", "title": "Birds' Nests", "start": "1885-09-21", "end": "1885-10-10", "display": "late September - early October 1885", "location": "http://vangoghmuseum.nl/data/term/1", "current_owner": "http://vocab.getty.edu/ulan/500275558", "link": "https://vangoghworldwide.org/data/artwork/F109r"}, {"fnumber": "F109v", "jhnumber": "JH1303", "museumid": "s0071V1962v", "title": "Self-Portrait", "start": "1887-07-11", "end": "1887-08-31", "display": "mid July - August 1887", "location": "http://vangoghmuseum.nl/data/term/2221", "current_owner": "http://vocab.getty.edu/ulan/500275558", "link": "https://vangoghworldwide.org/data/artwork/F109v"}, {"fnumber": "F164", "jhnumber": "JH558", "museumid": "s0069V1962", "title": "Head of a Man", "start": "1884-11-01", "end": "1885-02-28", "display": "November 1884 - February 1885", "location": "http://vangoghmuseum.nl/data/term/1", "current_owner": "http://vocab.getty.edu/ulan/500275558", "link": "https://vangoghworldwide.org/data/artwork/F164"}, {"fnumber": "F103", "jhnumber": "JH928", "museumid": "s0070V1962", "title": "Still Life with Vegetables and Fruit", "start": "1884-09-01", "end": "1884-11-30", "display": "autumn 1884", "location": "http://vangoghmuseum.nl/data/term/1", "current_owner": "http://vocab.getty.edu/ulan/500275558", "link": "https://vangoghworldwide.org/data/artwork/F103"}, {"fnumber": "F179v", "jhnumber": "JH1300", "museumid": "s0068V1962v", "title": "Self-Portrait with Straw Hat and Pipe", "start": "1887-07-11", "end": "1887-08-31", "display": "mid July - August 1887", "location": "http://vangoghmuseum.nl/data/term/2221", "current_owner": "http://vocab.getty.edu/ulan/500275558", "link": "https://vangoghworldwide.org/data/artwork/F179v"}, {"fnumber": "F423", "jhnumber": "JH1486", "museumid": "s0067V1962", "title": "The Zouave", "start": "1888-06-01", "end": "1888-06-30", "display": "June 1888", "location": "http://vangoghmuseum.nl/data/term/41", "current_owner": "http://vocab.getty.edu/ulan/500275558", "link": "https://vangoghworldwide.org/data/artwork/F423"}, {"fnumber": "F179r", "jhnumber": "JH786", "museumid": "s0068V1962r", "title": "Head of a Man", "start": "1885-03-01", "end": "1885-05-30", "display": "March - May 1885", "location": "http://vangoghmuseum.nl/data/term/1", "current_owner": "http://vocab.getty.edu/ulan/500275558", "link": "https://vangoghworldwide.org/data/artwork/F179r"}, {"fnumber": "F356", "jhnumber": "JH1248", "museumid": "s0065V1962", "title": "Self-Portrait", "start": "1887-03-01", "end": "1887-06-30", "display": "March - June 1887", "location": "http://vangoghmuseum.nl/data/term/2221", "current_owner": "http://vocab.getty.edu/ulan/500275558", "link": "https://vangoghworldwide.org/data/artwork/F356"}, {"fnumber": "F229", "jhnumber": "JH1176", "museumid": "s0064V1962", "title": "The Hill of Montmartre with Stone Quarry", "start": "1886-06-01", "end": "1886-07-20", "display": "June - mid July 1886", "location": "http://vangoghmuseum.nl/data/term/2221", "current_owner": "http://vocab.getty.edu/ulan/500275558", "link": "https://vangoghworldwide.org/data/artwork/F229"}, {"fnumber": "F309a", "jhnumber": "JH1312", "museumid": "s0066V1962", "title": "Trees and Undergrowth", "start": "1887-07-16", "end": "1887-07-30", "display": "second half of July 1887", "location": "http://vangoghmuseum.nl/data/term/2221", "current_owner": "http://vocab.getty.edu/ulan/500275558", "link": "https://vangoghworldwide.org/data/artwork/F309a"}, {"fnumber": "F205", "jhnumber": "JH971", "museumid": "s0061V1962", "title": "Portrait of an Old Man", "start": "1885-12-07", "end": "1885-12-08", "display": "7 December or 8 December 1885", "location": "http://vangoghmuseum.nl/data/term/2269", "current_owner": "http://vocab.getty.edu/ulan/500275558", "link": "https://vangoghworldwide.org/data/artwork/F205"}, {"fnumber": "F336", "jhnumber": "JH1227", "museumid": "s0063V1962", "title": "Basket of Hyacinth Bulbs", "start": "1887-01-01", "end": "1887-02-28", "display": "January - February 1887", "location": "http://vangoghmuseum.nl/data/term/2221", "current_owner": "http://vocab.getty.edu/ulan/500275558", "link": "https://vangoghworldwide.org/data/artwork/F336"}, {"fnumber": "F80a", "jhnumber": "JH682", "museumid": "s0062V1962", "title": "Head of a Woman", "start": "1885-03-01", "end": "1885-03-28", "display": "March 1885", "location": "http://vangoghmuseum.nl/data/term/1", "current_owner": "http://vocab.getty.edu/ulan/500275558", "link": "https://vangoghworldwide.org/data/artwork/F80a"}, {"fnumber": "F61r", "jhnumber": "JH533", "museumid": "s0060V1962r", "title": "Still Life with Bottles and Earthenware", "start": "1884-11-01", "end": "1885-04-30", "display": "November 1884 - April 1885", "location": "http://vangoghmuseum.nl/data/term/1", "current_owner": "http://vocab.getty.edu/ulan/500275558", "link": "https://vangoghworldwide.org/data/artwork/F61r"}, {"fnumber": "F61v", "jhnumber": "JH1302", "museumid": "s0060V1962v", "title": "Self-Portrait with Straw Hat", "start": "1887-07-11", "end": "1887-08-31", "display": "mid July - August 1887", "location": "http://vangoghmuseum.nl/data/term/2221", "current_owner": "http://vocab.getty.edu/ulan/500275558", "link": "https://vangoghworldwide.org/data/artwork/F61v"}, {"fnumber": "F206", "jhnumber": "JH972", "museumid": "s0059V1962", "title": "Head of a Woman", "start": "1885-12-11", "end": "1885-12-30", "display": "mid - late December 1885", "location": "http://vangoghmuseum.nl/data/term/2269", "current_owner": "http://vocab.getty.edu/ulan/500275558", "link": "https://vangoghworldwide.org/data/artwork/F206"}, {"fnumber": "F216a", "jhnumber": "JH1054", "museumid": "s0056V1962", "title": "Torso of Venus", "start": "1886-06-11", "end": "1886-06-20", "display": "mid June 1886", "location": "http://vangoghmuseum.nl/data/term/2221", "current_owner": "http://vocab.getty.edu/ulan/500275558", "link": "https://vangoghworldwide.org/data/artwork/F216a"}, {"fnumber": "F161", "jhnumber": "JH788", "museumid": "s0058V1962", "title": "Woman with a Mourning Shawl", "start": "1885-03-01", "end": "1885-05-30", "display": "March - May 1885", "location": "http://vangoghmuseum.nl/data/term/1", "current_owner": "http://vocab.getty.edu/ulan/500275558", "link": "https://vangoghworldwide.org/data/artwork/F161"}, {"fnumber": "F341", "jhnumber": "JH1242", "museumid": "s0057V1962", "title": "View from Theo's Apartment", "start": "1887-03-21", "end": "1887-04-20", "display": "late March - mid April 1887", "location": "http://vangoghmuseum.nl/data/term/2221", "current_owner": "http://vocab.getty.edu/ulan/500275558", "link": "https://vangoghworldwide.org/data/artwork/F341"}, {"fnumber": "F17", "jhnumber": "JH395", "museumid": "s0053V1962", "title": "Cottages", "start": "1883-09-11", "end": "1883-11-20", "display": "mid September - mid November 1883", "location": "http://vangoghmuseum.nl/data/term/3551", "current_owner": "http://vocab.getty.edu/ulan/500275558", "link": "https://vangoghworldwide.org/data/artwork/F17"}, {"fnumber": "F299", "jhnumber": "JH1254", "museumid": "s0055V1962", "title": "By the Seine", "start": "1887-05-11", "end": "1887-07-30", "display": "mid May - late July 1887", "location": "http://vangoghmuseum.nl/data/term/2221", "current_owner": "http://vocab.getty.edu/ulan/500275558", "link": "https://vangoghworldwide.org/data/artwork/F299"}, {"fnumber": "F175", "jhnumber": "JH497", "museumid": "s0054V1962", "title": "Bobbin Winder", "start": "1885-03-01", "end": "1885-04-30", "display": "March - April 1885", "location": "http://vangoghmuseum.nl/data/term/1", "current_owner": "http://vocab.getty.edu/ulan/500275558", "link": "https://vangoghworldwide.org/data/artwork/F175"}, {"fnumber": "F51", "jhnumber": "JH925", "museumid": "s0052V1962", "title": "Still Life with Brass Cauldron and Jug", "start": "1885-09-01", "end": "1885-09-30", "display": "September 1885", "location": "http://vangoghmuseum.nl/data/term/1", "current_owner": "http://vocab.getty.edu/ulan/500275558", "link": "https://vangoghworldwide.org/data/artwork/F51"}, {"fnumber": "F746", "jhnumber": "JH1762", "museumid": "s0051V1962", "title": "Undergrowth", "start": "1889-07-01", "end": "1889-07-15", "display": "first half of July 1889", "location": "http://vangoghmuseum.nl/data/term/2229", "current_owner": "http://vocab.getty.edu/ulan/500275558", "link": "https://vangoghworldwide.org/data/artwork/F746"}, {"fnumber": "F618", "jhnumber": "JH1773", "museumid": "s0049V1962", "title": "Wheatfield with a Reaper", "start": "1889-09-01", "end": "1889-09-10", "display": "early September 1889", "location": "http://vangoghmuseum.nl/data/term/2229", "current_owner": "http://vocab.getty.edu/ulan/500275558", "link": "https://vangoghworldwide.org/data/artwork/F618"}, {"fnumber": "F678", "jhnumber": "JH1977", "museumid": "s0050V1962", "title": "Irises", "start": "1890-05-01", "end": "1890-05-30", "display": "May 1890", "location": "http://vangoghmuseum.nl/data/term/2229", "current_owner": "http://vocab.getty.edu/ulan/500275558", "link": "https://vangoghworldwide.org/data/artwork/F678"}, {"fnumber": "F499", "jhnumber": "JH1636", "museumid": "s0048V1962", "title": "Gauguin's Chair", "start": "1888-11-01", "end": "1888-11-30", "display": "November 1888", "location": "http://vangoghmuseum.nl/data/term/41", "current_owner": "http://vocab.getty.edu/ulan/500275558", "link": "https://vangoghworldwide.org/data/artwork/F499"}, {"fnumber": "F651", "jhnumber": "JH1844", "museumid": "s0046V1962", "title": "The Garden of Saint Paul's Hospital ('Leaf-Fall')", "start": "1889-10-01", "end": "1889-10-30", "display": "October 1889", "location": "http://vangoghmuseum.nl/data/term/2229", "current_owner": "http://vocab.getty.edu/ulan/500275558", "link": "https://vangoghworldwide.org/data/artwork/F651"}, {"fnumber": "F482", "jhnumber": "JH1608", "museumid": "s0047V1962", "title": "The Bedroom", "start": "1888-10-11", "end": "1888-10-20", "display": "mid October 1888", "location": "http://vangoghmuseum.nl/data/term/41", "current_owner": "http://vocab.getty.edu/ulan/500275558", "link": "https://vangoghworldwide.org/data/artwork/F482"}, {"fnumber": "F709", "jhnumber": "JH1760", "museumid": "s0044V1962", "title": "Olive Grove", "start": "1889-06-01", "end": "1889-06-30", "display": "June 1889", "location": "http://vangoghmuseum.nl/data/term/2229", "current_owner": "http://vocab.getty.edu/ulan/500275558", "link": "https://vangoghworldwide.org/data/artwork/F709"}, {"fnumber": "F697", "jhnumber": "JH1788", "museumid": "s0043V1962", "title": "Peasant Woman Bruising Flax (after Millet)", "start": "1889-09-11", "end": "1889-09-20", "display": "mid September 1889", "location": "http://vangoghmuseum.nl/data/term/2229", "current_owner": "http://vocab.getty.edu/ulan/500275558", "link": "https://vangoghworldwide.org/data/artwork/F697"}, {"fnumber": "F707", "jhnumber": "JH1857", "museumid": "s0045V1962", "title": "Olive Grove", "start": "1889-11-01", "end": "1889-12-30", "display": "November - December 1889", "location": "http://vangoghmuseum.nl/data/term/2229", "current_owner": "http://vocab.getty.edu/ulan/500275558", "link": "https://vangoghworldwide.org/data/artwork/F707"}, {"fnumber": "F744", "jhnumber": "JH1802", "museumid": "s0041V1962", "title": "Entrance to a Quarry", "start": "1889-07-11", "end": "1889-07-20", "display": "mid July 1889", "location": "http://vangoghmuseum.nl/data/term/2229", "current_owner": "http://vocab.getty.edu/ulan/500275558", "link": "https://vangoghworldwide.org/data/artwork/F744"}, {"fnumber": "F574", "jhnumber": "JH1586", "museumid": "s0040V1962", "title": "Ploughed Fields ('The Furrows')", "start": "1888-09-01", "end": "1888-09-30", "display": "September 1888", "location": "http://vangoghmuseum.nl/data/term/41", "current_owner": "http://vocab.getty.edu/ulan/500275558", "link": "https://vangoghworldwide.org/data/artwork/F574"}, {"fnumber": "F634", "jhnumber": "JH1787", "museumid": "s0042V1962", "title": "The Sheepshearer (after Millet)", "start": "1889-09-18", "end": "1889-09-22", "display": "circa 20 September 1889", "location": "http://vangoghmuseum.nl/data/term/2229", "current_owner": "http://vocab.getty.edu/ulan/500275558", "link": "https://vangoghworldwide.org/data/artwork/F634"}, {"fnumber": "F405", "jhnumber": "JH1394", "museumid": "s0039V1962", "title": "Small Pear Tree in Blossom", "start": "1888-04-11", "end": "1888-04-20", "display": "mid April 1888", "location": "http://vangoghmuseum.nl/data/term/41", "current_owner": "http://vocab.getty.edu/ulan/500275558", "link": "https://vangoghworldwide.org/data/artwork/F405"}, {"fnumber": "F511", "jhnumber": "JH1386", "museumid": "s0038V1962", "title": "Orchard in Blossom", "start": "1889-04-01", "end": "1889-04-30", "display": "April 1889", "location": "http://vangoghmuseum.nl/data/term/41", "current_owner": "http://vocab.getty.edu/ulan/500275558", "link": "https://vangoghworldwide.org/data/artwork/F511"}, {"fnumber": "F409", "jhnumber": "JH1416", "museumid": "s0037V1962", "title": "Field with Irises near Arles", "start": "1888-05-01", "end": "1888-05-15", "display": "first half of May 1888", "location": "http://vangoghmuseum.nl/data/term/41", "current_owner": "http://vocab.getty.edu/ulan/500275558", "link": "https://vangoghworldwide.org/data/artwork/F409"}, {"fnumber": "F557", "jhnumber": "JH1397", "museumid": "s0035V1962", "title": "Peach Tree in Blossom", "start": "1888-04-01", "end": "1888-04-30", "display": "April 1888", "location": "http://vangoghmuseum.nl/data/term/41", "current_owner": "http://vocab.getty.edu/ulan/500275558", "link": "https://vangoghworldwide.org/data/artwork/F557"}, {"fnumber": "F515", "jhnumber": "JH1683", "museumid": "s0036V1962", "title": "Orchards in Blossom, View of Arles", "start": "1889-04-01", "end": "1889-04-30", "display": "April 1889", "location": "http://vangoghmuseum.nl/data/term/41", "current_owner": "http://vocab.getty.edu/ulan/500275558", "link": "https://vangoghworldwide.org/data/artwork/F515"}, {"fnumber": "F576", "jhnumber": "JH1423", "museumid": "s0033V1962", "title": "Field with Poppies", "start": "1888-05-01", "end": "1888-05-30", "display": "May 1888", "location": "http://vangoghmuseum.nl/data/term/41", "current_owner": "http://vocab.getty.edu/ulan/500275558", "link": "https://vangoghworldwide.org/data/artwork/F576"}, {"fnumber": "F464", "jhnumber": "JH1589", "museumid": "s0032V1962", "title": "The Yellow House (The Street)", "start": "1888-09-01", "end": "1888-09-30", "display": "September 1888", "location": "http://vangoghmuseum.nl/data/term/41", "current_owner": "http://vocab.getty.edu/ulan/500275558", "link": "https://vangoghworldwide.org/data/artwork/F464"}, {"fnumber": "F408", "jhnumber": "JH1417", "museumid": "s0034V1962", "title": "Farmhouse in a Wheatfield", "start": "1888-05-01", "end": "1888-05-15", "display": "first half of May 1888", "location": "http://vangoghmuseum.nl/data/term/41", "current_owner": "http://vocab.getty.edu/ulan/500275558", "link": "https://vangoghworldwide.org/data/artwork/F408"}, {"fnumber": "F458", "jhnumber": "JH1667", "museumid": "s0031V1962", "title": "Sunflowers", "start": "1889-01-16", "end": "1889-01-31", "display": "second half of January 1889", "location": "http://vangoghmuseum.nl/data/term/41", "current_owner": "http://vocab.getty.edu/ulan/500275558", "link": "https://vangoghworldwide.org/data/artwork/F458"}, {"fnumber": "F412", "jhnumber": "JH1440", "museumid": "s0030V1962", "title": "The Harvest", "start": "1888-06-11", "end": "1888-06-16", "display": "11-16 June 1888", "location": "http://vangoghmuseum.nl/data/term/41", "current_owner": "http://vocab.getty.edu/ulan/500275558", "link": "https://vangoghworldwide.org/data/artwork/F412"}, {"fnumber": "F413", "jhnumber": "JH1460", "museumid": "s0028V1962", "title": "Fishing Boats on the Beach at Les Saintes-Maries-de-la-Mer", "start": "1888-06-01", "end": "1888-06-15", "display": "first half of June 1888", "location": "http://vangoghmuseum.nl/data/term/41", "current_owner": "http://vocab.getty.edu/ulan/500275558", "link": "https://vangoghworldwide.org/data/artwork/F413"}, {"fnumber": "F451", "jhnumber": "JH1629", "museumid": "s0029V1962", "title": "The Sower", "start": "1888-11-21", "end": "1888-11-30", "display": "late November 1888", "location": "http://vangoghmuseum.nl/data/term/41", "current_owner": "http://vocab.getty.edu/ulan/500275558", "link": "https://vangoghworldwide.org/data/artwork/F451"}, {"fnumber": "F555", "jhnumber": "JH1380", "museumid": "s0026V1962", "title": "The Pink Orchard", "start": "1888-04-01", "end": "1888-04-30", "display": "April 1888", "location": "http://vangoghmuseum.nl/data/term/41", "current_owner": "http://vocab.getty.edu/ulan/500275558", "link": "https://vangoghworldwide.org/data/artwork/F555"}, {"fnumber": "F400", "jhnumber": "JH1371", "museumid": "s0027V1962", "title": "The Langlois Bridge", "start": "1888-03-01", "end": "1888-03-29", "display": "March 1888", "location": "http://vangoghmuseum.nl/data/term/41", "current_owner": "http://vocab.getty.edu/ulan/500275558", "link": "https://vangoghworldwide.org/data/artwork/F400"}, {"fnumber": "F404", "jhnumber": "JH1391", "museumid": "s0025V1962", "title": "The Pink Peach Tree", "start": "1888-04-01", "end": "1888-05-30", "display": "April - May 1888", "location": "http://vangoghmuseum.nl/data/term/41", "current_owner": "http://vocab.getty.edu/ulan/500275558", "link": "https://vangoghworldwide.org/data/artwork/F404"}, {"fnumber": "F403", "jhnumber": "JH1378", "museumid": "s0024V1962", "title": "The White Orchard", "start": "1888-04-01", "end": "1888-04-30", "display": "April 1888", "location": "http://vangoghmuseum.nl/data/term/41", "current_owner": "http://vocab.getty.edu/ulan/500275558", "link": "https://vangoghworldwide.org/data/artwork/F403"}, {"fnumber": "F383", "jhnumber": "JH1339", "museumid": "s0023V1962", "title": "Quinces, Lemons, Pears and Grapes", "start": "1887-09-01", "end": "1887-10-30", "display": "September - October 1887", "location": "http://vangoghmuseum.nl/data/term/2221", "current_owner": "http://vocab.getty.edu/ulan/500275558", "link": "https://vangoghworldwide.org/data/artwork/F383"}, {"fnumber": "F358", "jhnumber": "JH1612", "museumid": "s0021V1962", "title": "Piles of French Novels", "start": "1887-10-01", "end": "1887-11-30", "display": "October - November 1887", "location": "http://vangoghmuseum.nl/data/term/2221", "current_owner": "http://vocab.getty.edu/ulan/500275558", "link": "https://vangoghworldwide.org/data/artwork/F358"}, {"fnumber": "F522", "jhnumber": "JH1356", "museumid": "s0022V1962", "title": "Self-Portrait as a Painter", "start": "1887-12-01", "end": "1888-02-29", "display": "December 1887 - February 1888", "location": "http://vangoghmuseum.nl/data/term/2221", "current_owner": "http://vocab.getty.edu/ulan/500275558", "link": "https://vangoghworldwide.org/data/artwork/F522"}, {"fnumber": "F340", "jhnumber": "JH1239", "museumid": "s0020V1962", "title": "Carafe and Dish with Citrus Fruit", "start": "1887-02-01", "end": "1887-03-28", "display": "February - March 1887", "location": "http://vangoghmuseum.nl/data/term/2221", "current_owner": "http://vocab.getty.edu/ulan/500275558", "link": "https://vangoghworldwide.org/data/artwork/F340"}, {"fnumber": "F314", "jhnumber": "JH1258", "museumid": "s0019V1962", "title": "Garden with Courting Couples: Square Saint-Pierre", "start": "1887-05-11", "end": "1887-05-30", "display": "mid - late May 1887", "location": "http://vangoghmuseum.nl/data/term/2221", "current_owner": "http://vocab.getty.edu/ulan/500275558", "link": "https://vangoghworldwide.org/data/artwork/F314"}, {"fnumber": "F316", "jhnumber": "JH1246", "museumid": "s0018V1962", "title": "Montmartre: Behind the Moulin de la Galette", "start": "1887-07-21", "end": "1887-07-30", "display": "late July 1887", "location": "http://vangoghmuseum.nl/data/term/2221", "current_owner": "http://vocab.getty.edu/ulan/500275558", "link": "https://vangoghworldwide.org/data/artwork/F316"}, {"fnumber": "F370", "jhnumber": "JH1208", "museumid": "s0017V1962", "title": "In the Caf\u00e9: Agostina Segatori in Le Tambourin", "start": "1887-01-01", "end": "1887-03-28", "display": "January - March 1887", "location": "http://vangoghmuseum.nl/data/term/2221", "current_owner": "http://vocab.getty.edu/ulan/500275558", "link": "https://vangoghworldwide.org/data/artwork/F370"}, {"fnumber": "F344", "jhnumber": "JH1353", "museumid": "s0016V1962", "title": "Self-Portrait with Grey Felt Hat", "start": "1887-09-01", "end": "1887-10-30", "display": "September - October 1887", "location": "http://vangoghmuseum.nl/data/term/2221", "current_owner": "http://vocab.getty.edu/ulan/500275558", "link": "https://vangoghworldwide.org/data/artwork/F344"}, {"fnumber": "F346", "jhnumber": "JH1244", "museumid": "s0015V1962", "title": "Montmartre: Windmills and Allotments", "start": "1887-03-01", "end": "1887-04-20", "display": "March - mid April 1887", "location": "http://vangoghmuseum.nl/data/term/2221", "current_owner": "http://vocab.getty.edu/ulan/500275558", "link": "https://vangoghworldwide.org/data/artwork/F346"}, {"fnumber": "F347", "jhnumber": "JH1241", "museumid": "s0014V1962", "title": "Impasse des Deux Fr\u00e8res", "start": "1887-02-21", "end": "1887-04-20", "display": "late February - mid April 1887", "location": "http://vangoghmuseum.nl/data/term/2221", "current_owner": "http://vocab.getty.edu/ulan/500275558", "link": "https://vangoghworldwide.org/data/artwork/F347"}, {"fnumber": "F261", "jhnumber": "JH1101", "museumid": "s0013V1962", "title": "View of Paris", "start": "1886-06-01", "end": "1886-07-30", "display": "June - July 1886", "location": "http://vangoghmuseum.nl/data/term/2221", "current_owner": "http://vocab.getty.edu/ulan/500275558", "link": "https://vangoghworldwide.org/data/artwork/F261"}, {"fnumber": "F230", "jhnumber": "JH1177", "museumid": "s0012V1962", "title": "The Hill of Montmartre with Stone Quarry", "start": "1886-06-01", "end": "1886-07-20", "display": "June - mid July 1886", "location": "http://vangoghmuseum.nl/data/term/2221", "current_owner": "http://vocab.getty.edu/ulan/500275558", "link": "https://vangoghworldwide.org/data/artwork/F230"}, {"fnumber": "F255", "jhnumber": "JH1124", "museumid": "s0011V1962", "title": "Shoes", "start": "1886-09-01", "end": "1886-11-30", "display": "September - November 1886", "location": "http://vangoghmuseum.nl/data/term/2221", "current_owner": "http://vocab.getty.edu/ulan/500275558", "link": "https://vangoghworldwide.org/data/artwork/F255"}, {"fnumber": "F174", "jhnumber": "JH978", "museumid": "s0010V1962", "title": "Portrait of an Old Woman", "start": "1885-12-11", "end": "1885-12-30", "display": "mid - late December 1885", "location": "http://vangoghmuseum.nl/data/term/2269", "current_owner": "http://vocab.getty.edu/ulan/500275558", "link": "https://vangoghworldwide.org/data/artwork/F174"}, {"fnumber": "F76", "jhnumber": "JH542", "museumid": "s0009V1962", "title": "Vase with Honesty", "start": "1884-09-01", "end": "1884-01-01", "display": "autumn - winter 1884", "location": "http://vangoghmuseum.nl/data/term/1", "current_owner": "http://vocab.getty.edu/ulan/500275558", "link": "https://vangoghworldwide.org/data/artwork/F76"}, {"fnumber": "F160", "jhnumber": "JH722", "museumid": "s0006V1962", "title": "Head of a Woman", "start": "1885-05-01", "end": "1885-05-30", "display": "May 1885", "location": "http://vangoghmuseum.nl/data/term/1", "current_owner": "http://vocab.getty.edu/ulan/500275558", "link": "https://vangoghworldwide.org/data/artwork/F160"}, {"fnumber": "F71", "jhnumber": "JH719", "museumid": "s0007V1962", "title": "Woman Sewing", "start": "1885-03-01", "end": "1885-04-30", "display": "March - April 1885", "location": "http://vangoghmuseum.nl/data/term/1", "current_owner": "http://vocab.getty.edu/ulan/500275558", "link": "https://vangoghworldwide.org/data/artwork/F71"}, {"fnumber": "F117", "jhnumber": "JH946", "museumid": "s0008V1962", "title": "Still Life with Bible", "start": "1885-10-01", "end": "1885-10-30", "display": "October 1885", "location": "http://vangoghmuseum.nl/data/term/1", "current_owner": "http://vocab.getty.edu/ulan/500275558", "link": "https://vangoghworldwide.org/data/artwork/F117"}, {"fnumber": "F82", "jhnumber": "JH764", "museumid": "s0005V1962", "title": "The Potato Eaters", "start": "1885-04-11", "end": "1885-05-10", "display": "mid April - early May 1885", "location": "http://vangoghmuseum.nl/data/term/1", "current_owner": "http://vocab.getty.edu/ulan/500275558", "link": "https://vangoghworldwide.org/data/artwork/F82"}, {"fnumber": "F388r", "jhnumber": "JH782", "museumid": "s0004V1962r", "title": "Head of a Woman", "start": "1885-05-01", "end": "1885-05-30", "display": "May 1885", "location": "http://vangoghmuseum.nl/data/term/1", "current_owner": "http://vocab.getty.edu/ulan/500275558", "link": "https://vangoghworldwide.org/data/artwork/F388r"}, {"fnumber": "F388v", "jhnumber": "JH1307", "museumid": "s0004V1962v", "title": "Allotment with Sunflower", "start": "1887-07-16", "end": "1887-07-30", "display": "second half of July 1887", "location": "http://vangoghmuseum.nl/data/term/2221", "current_owner": "http://vocab.getty.edu/ulan/500275558", "link": "https://vangoghworldwide.org/data/artwork/F388v"}, {"fnumber": "F84", "jhnumber": "JH772", "museumid": "s0002V1962", "title": "The Old Church Tower at Nuenen ('The Peasants' Churchyard')", "start": "1885-05-21", "end": "1885-06-10", "display": "late May - early June 1885", "location": "http://vangoghmuseum.nl/data/term/1", "current_owner": "http://vocab.getty.edu/ulan/500275558", "link": "https://vangoghworldwide.org/data/artwork/F84"}, {"fnumber": "F25", "jhnumber": "JH521", "museumid": "s0003V1962", "title": "Congregation Leaving the Reformed Church in Nuenen", "start": "1885-09-01", "end": "1885-11-30", "display": "January - February 1884", "location": "http://vangoghmuseum.nl/data/term/1", "current_owner": "http://vocab.getty.edu/ulan/500275558", "link": "https://vangoghworldwide.org/data/artwork/F25"}, {"fnumber": "F25", "jhnumber": "JH521", "museumid": "s0003V1962", "title": "Congregation Leaving the Reformed Church in Nuenen", "start": "1884-01-01", "end": "1885-11-30", "display": "autumn 1885", "location": "http://vangoghmuseum.nl/data/term/1", "current_owner": "http://vocab.getty.edu/ulan/500275558", "link": "https://vangoghworldwide.org/data/artwork/F25"}, {"fnumber": "F25", "jhnumber": "JH521", "museumid": "s0003V1962", "title": "Congregation Leaving the Reformed Church in Nuenen", "start": "1884-01-01", "end": "1884-02-29", "display": "January - February 1884", "location": "http://vangoghmuseum.nl/data/term/1", "current_owner": "http://vocab.getty.edu/ulan/500275558", "link": "https://vangoghworldwide.org/data/artwork/F25"}, {"fnumber": "F25", "jhnumber": "JH521", "museumid": "s0003V1962", "title": "Congregation Leaving the Reformed Church in Nuenen", "start": "1885-09-01", "end": "1884-02-29", "display": "autumn 1885", "location": "http://vangoghmuseum.nl/data/term/1", "current_owner": "http://vocab.getty.edu/ulan/500275558", "link": "https://vangoghworldwide.org/data/artwork/F25"}, {"fnumber": "F25", "jhnumber": "JH521", "museumid": "s0003V1962", "title": "Congregation Leaving the Reformed Church in Nuenen", "start": "1885-09-01", "end": "1884-02-29", "display": "January - February 1884", "location": "http://vangoghmuseum.nl/data/term/1", "current_owner": "http://vocab.getty.edu/ulan/500275558", "link": "https://vangoghworldwide.org/data/artwork/F25"}, {"fnumber": "F25", "jhnumber": "JH521", "museumid": "s0003V1962", "title": "Congregation Leaving the Reformed Church in Nuenen", "start": "1884-01-01", "end": "1884-02-29", "display": "autumn 1885", "location": "http://vangoghmuseum.nl/data/term/1", "current_owner": "http://vocab.getty.edu/ulan/500275558", "link": "https://vangoghworldwide.org/data/artwork/F25"}, {"fnumber": "F25", "jhnumber": "JH521", "museumid": "s0003V1962", "title": "Congregation Leaving the Reformed Church in Nuenen", "start": "1884-01-01", "end": "1885-11-30", "display": "January - February 1884", "location": "http://vangoghmuseum.nl/data/term/1", "current_owner": "http://vocab.getty.edu/ulan/500275558", "link": "https://vangoghworldwide.org/data/artwork/F25"}, {"fnumber": "F25", "jhnumber": "JH521", "museumid": "s0003V1962", "title": "Congregation Leaving the Reformed Church in Nuenen", "start": "1885-09-01", "end": "1885-11-30", "display": "autumn 1885", "location": "http://vangoghmuseum.nl/data/term/1", "current_owner": "http://vocab.getty.edu/ulan/500275558", "link": "https://vangoghworldwide.org/data/artwork/F25"}, {"fnumber": "F111", "jhnumber": "JH939", "museumid": "s0001V1962", "title": "Birds' Nests", "start": "1885-09-21", "end": "1885-10-10", "display": "late September - early October 1885", "location": "http://vangoghmuseum.nl/data/term/1", "current_owner": "http://vocab.getty.edu/ulan/500275558", "link": "https://vangoghworldwide.org/data/artwork/F111"}]